pytest_joke/__init__.py
pytest_joke/plugin.py
pytest_joke-0.1.1.dist-info/LICENSE
pytest_joke-0.1.1.dist-info/METADATA
pytest_joke-0.1.1.dist-info/WHEEL
pytest_joke-0.1.1.dist-info/entry_points.txt
pytest_joke-0.1.1.dist-info/top_level.txt
pytest_joke-0.1.1.dist-info/RECORD
