Metadata-Version: 2.1
Name: pytest-joke
Version: 0.1.1
Summary: Test failures are better served with humor.
Home-page: https://github.com/alecxe/pytest-joke
Author: Alexander Afanasyev
Author-email: me@alecxe.me
Maintainer: Alexander Afanasyev
Maintainer-email: me@alecxe.me
License: MIT
Keywords: pytest,joke,humor,humour
Platform: UNKNOWN
Classifier: Development Status :: 4 - Beta
Classifier: Framework :: Pytest
Classifier: Intended Audience :: Developers
Classifier: Topic :: Software Development :: Testing
Classifier: Programming Language :: Python
Classifier: Programming Language :: Python :: 3
Classifier: Programming Language :: Python :: 3.4
Classifier: Programming Language :: Python :: 3.5
Classifier: Programming Language :: Python :: 3.6
Classifier: Programming Language :: Python :: 3.7
Classifier: Programming Language :: Python :: Implementation :: CPython
Classifier: Operating System :: OS Independent
Classifier: License :: OSI Approved :: MIT License
Requires-Python: >=3.4
Requires-Dist: pytest (>=4.2.1)
Requires-Dist: pyjokes (>=0.6.0)
